burningalice/__init__.py
burningalice/auto_label_tracker.py
burningalice/map_analyzer.py
burningalice/metrics_tracker.py
burningalice/text_config_generator.py
burningalice/text_tracker.py
burningalice-0.0.17.dist-info/LICENSE
burningalice-0.0.17.dist-info/METADATA
burningalice-0.0.17.dist-info/WHEEL
burningalice-0.0.17.dist-info/top_level.txt
burningalice-0.0.17.dist-info/RECORD
